unique_files/__init__.py
unique_files/scripts/__init__.py
unique_files/scripts/unique_files.py
unique_files/unique_files.py
unique_files-0.1.0.dist-info/entry_points.txt
unique_files-0.1.0.dist-info/WHEEL
unique_files-0.1.0.dist-info/METADATA
unique_files-0.1.0.dist-info/RECORD
